{
  "feed_metadata": {
    "shard_id": 0,
    "total_shards_count": 1,
    "processing_instruction": "PROCESS_AS_SNAPSHOT",
    "nonce": 202603300591
  },
  "products": [
    {
      "id": "product-659",
      "title": {
        "localized_texts": [
          {
            "language_code": "en",
            "text": "Breakout Escape Game NU Sentral"
          }
        ]
      },
      "description": {
        "localized_texts": [
          {
            "language_code": "en",
            "text": "Whether you prefer an experience that challenges your brains, your physical stamina or just want to have fun time together, we’ve got them all here! Our escape rooms and spy game missions come with many difficulty levels, a variety of physical agility requirements and also family friendly option suitable for the younger one. For the horror fans, check out Breakout’s sister brand Hauntu for a different, unique and terrifying experience."
          }
        ]
      },
      "rating": {
        "average_value": 4.3,
        "rating_count": 100
      },
      "product_features": [
        {
          "feature_type": "TEXT_FEATURE_HIGHLIGHT",
          "value": {
            "localized_texts": [
              {
                "language_code": "en",
                "text": "Escape game that comes with realistic design & props, an engaging storyline that immerses you in to the gameplay."
              }
            ]
          }
        },
        {
          "feature_type": "TEXT_FEATURE_HIGHLIGHT",
          "value": {
            "localized_texts": [
              {
                "language_code": "en",
                "text": "Every theme room can accommodate between 2-8 players."
              }
            ]
          }
        },
        {
          "feature_type": "TEXT_FEATURE_HIGHLIGHT",
          "value": {
            "localized_texts": [
              {
                "language_code": "en",
                "text": "Solve exciting missions, engaging puzzles, and obstacles and escape within 55 minutes."
              }
            ]
          }
        },
        {
          "feature_type": "TEXT_FEATURE_INCLUSION",
          "value": {
            "localized_texts": [
              {
                "language_code": "en",
                "text": "Get ready for an unforgettable adventure at Breakout NU Sentral, where you’ll step into 7 unique themed escape rooms.&nbsp;100% Original Storylines - Immerse yourself in creative, never-before-seen narratives that will keep you on the edge of your seat. Each room has its own story to tell, making every experience distinct and exciting.Varying Levels of Difficulty - Whether you're a seasoned escape room enthusiast or a first-timer, we’ve got rooms with a range of difficulty levels to challenge everyone. From beginner-friendly to brain-bending puzzles, there’s something for everyone.Unique &amp; Unrepeated Puzzles - Prepare to be amazed by original puzzles designed to keep you guessing! Each room features intricate, never-repeated challenges that require teamwork, creativity, and problem-solving skills to conquer.The Wow Factor - Expect the unexpected! Our rooms are built with impressive, immersive designs and innovative mechanics that will truly wow you from start to finish. You’ll feel like you're stepping into a completely different world."
              }
            ]
          }
        },
        {
          "feature_type": "TEXT_FEATURE_MUST_KNOW",
          "value": {
            "localized_texts": [
              {
                "language_code": "en",
                "text": "Wear comfortable clothing and shoes suitable for light movement and activity"
              }
            ]
          }
        },
        {
          "feature_type": "TEXT_FEATURE_MUST_KNOW",
          "value": {
            "localized_texts": [
              {
                "language_code": "en",
                "text": "Listen carefully to the pre-game briefing and follow the game rules set by the staff."
              }
            ]
          }
        },
        {
          "feature_type": "TEXT_FEATURE_MUST_KNOW",
          "value": {
            "localized_texts": [
              {
                "language_code": "en",
                "text": "Arrive at least 15 minutes before your scheduled game time for briefing and instructions."
              }
            ]
          }
        },
        {
          "feature_type": "TEXT_FEATURE_INCLUSION",
          "value": {
            "localized_texts": [
              {
                "language_code": "en",
                "text": "What’s included: Admission at Breakout Nu Sentral"
              }
            ]
          }
        },
        {
          "feature_type": "TEXT_FEATURE_INCLUSION",
          "value": {
            "localized_texts": [
              {
                "language_code": "en",
                "text": "What’s included: Customer can choose 1 of the listed games: The War for Rembrandt, Materia Medica, Secret of Hocus (minimum 3 players), Terraform, Testament of Tesla (minimum 3 players), Perpetual"
              }
            ]
          }
        },
        {
          "feature_type": "TEXT_FEATURE_MUST_KNOW",
          "value": {
            "localized_texts": [
              {
                "language_code": "en",
                "text": "How to use: Show Mobile Ticket: Ticketing counter"
              }
            ]
          }
        },
        {
          "feature_type": "TEXT_FEATURE_MUST_KNOW",
          "value": {
            "localized_texts": [
              {
                "language_code": "en",
                "text": "How to use: Once a ticket is purchased, please WhatsApp 6012-683 3628 for the steps and instructions to book your preferred timeslot. Additionally, we are reachable on social media (IG: @breakoutmy & FB: Breakout Malaysia)"
              }
            ]
          }
        },
        {
          "feature_type": "TEXT_FEATURE_MUST_KNOW",
          "value": {
            "localized_texts": [
              {
                "language_code": "en",
                "text": "Terms & Conditions: If customers are late for less than 10 minutes, the game will start and the experience time will be shortened. If customers are late for more than 10 minutes, the game will be rescheduled with another available time slot (subject to availability of the game session). If customers arrive with fewer participants than the purchase amount, no refund will be available. Additional players will be charged accordingly. Children aged 7 and below can play for FREE. Children aged 12 and below must be accompanied by a guardian who is 18 years old or above inside the room to play with them. Underage teens aged 13-17 will require a guardian to be present, and the guardian must sign a consent form before the teens are allowed to play alone."
              }
            ]
          }
        },
        {
          "feature_type": "TEXT_FEATURE_MUST_KNOW",
          "value": {
            "localized_texts": [
              {
                "language_code": "en",
                "text": "Cancellation Policy: Free cancellation till validity ends."
              }
            ]
          }
        },
        {
          "feature_type": "TEXT_FEATURE_INCLUSION",
          "value": {
            "localized_texts": [
              {
                "language_code": "en",
                "text": "What’s included: This package is entitled for the game: Final Hour (75-minutes gameplay with Live Actor / NPC, minimum 3 players) only"
              }
            ]
          }
        }
      ],
      "options": [
        {
          "id": "option-1",
          "title": {
            "localized_texts": [
              {
                "language_code": "en",
                "text": "Breakout NU Sentral [2 Pax] - Choose one: The War for Rembrandt / Materia Medica Secret of Hocus / Terraform / Testament of Tesla / Perpetual"
              }
            ]
          },
          "landing_page": {
            "url": "https://www.redbus.my/things-to-do/malaysia/kuala-lumpur/breakout-escape-game-nu-sentral"
          },
          "cancellation_policy": {},
          "option_categories": [
            {
              "label": "amusement-theme-park"
            }
          ],
          "related_locations": [
            {
              "location": {
                "location": {
                  "place_id": "ChIJV2x9oY1JzDER5l8k2n7p4Q"
                }
              },
              "relation_type": "RELATION_TYPE_ADMISSION_TICKET"
            }
          ],
          "price_options": [
            {
              "id": "option-1-per-pax",
              "title": "Per Pax (3–99 yrs)",
              "price": {
                "currency_code": "MYR",
                "units": 48
              }
            }
          ]
        },
        {
          "id": "option-2",
          "title": {
            "localized_texts": [
              {
                "language_code": "en",
                "text": "Breakout NU Sentral [3 - 4 Pax] - Choose one: The War for Rembrandt / Materia Medica Secret of Hocus / Terraform / Testament of Tesla / Perpetual"
              }
            ]
          },
          "landing_page": {
            "url": "https://www.redbus.my/things-to-do/malaysia/kuala-lumpur/breakout-escape-game-nu-sentral"
          },
          "cancellation_policy": {},
          "option_categories": [
            {
              "label": "amusement-theme-park"
            }
          ],
          "related_locations": [
            {
              "location": {
                "location": {
                  "place_id": "ChIJV2x9oY1JzDER5l8k2n7p4Q"
                }
              },
              "relation_type": "RELATION_TYPE_ADMISSION_TICKET"
            }
          ],
          "price_options": [
            {
              "id": "option-2-per-pax",
              "title": "Per Pax (3–99 yrs)",
              "price": {
                "currency_code": "MYR",
                "units": 42
              }
            }
          ]
        },
        {
          "id": "option-3",
          "title": {
            "localized_texts": [
              {
                "language_code": "en",
                "text": "Breakout NU Sentral [5 - 6 Pax] - Choose one: The War for Rembrandt / Materia Medica Secret of Hocus / Terraform / Testament of Tesla / Perpetual"
              }
            ]
          },
          "landing_page": {
            "url": "https://www.redbus.my/things-to-do/malaysia/kuala-lumpur/breakout-escape-game-nu-sentral"
          },
          "cancellation_policy": {},
          "option_categories": [
            {
              "label": "amusement-theme-park"
            }
          ],
          "related_locations": [
            {
              "location": {
                "location": {
                  "place_id": "ChIJV2x9oY1JzDER5l8k2n7p4Q"
                }
              },
              "relation_type": "RELATION_TYPE_ADMISSION_TICKET"
            }
          ],
          "price_options": [
            {
              "id": "option-3-per-pax",
              "title": "Per Pax (3–99 yrs)",
              "price": {
                "currency_code": "MYR",
                "units": 36
              }
            }
          ]
        },
        {
          "id": "option-4",
          "title": {
            "localized_texts": [
              {
                "language_code": "en",
                "text": "Breakout NU Sentral [7 - 8 Pax] - Choose one: The War for Rembrandt / Materia Medica Secret of Hocus / Terraform / Testament of Tesla / Perpetual"
              }
            ]
          },
          "landing_page": {
            "url": "https://www.redbus.my/things-to-do/malaysia/kuala-lumpur/breakout-escape-game-nu-sentral"
          },
          "cancellation_policy": {},
          "option_categories": [
            {
              "label": "amusement-theme-park"
            }
          ],
          "related_locations": [
            {
              "location": {
                "location": {
                  "place_id": "ChIJV2x9oY1JzDER5l8k2n7p4Q"
                }
              },
              "relation_type": "RELATION_TYPE_ADMISSION_TICKET"
            }
          ],
          "price_options": [
            {
              "id": "option-4-per-pax",
              "title": "Per Pax (3–99 yrs)",
              "price": {
                "currency_code": "MYR",
                "units": 36
              }
            }
          ]
        },
        {
          "id": "option-5",
          "title": {
            "localized_texts": [
              {
                "language_code": "en",
                "text": "Breakout NU Sentral [3 - 4 Pax]: Final Hour"
              }
            ]
          },
          "landing_page": {
            "url": "https://www.redbus.my/things-to-do/malaysia/kuala-lumpur/breakout-escape-game-nu-sentral"
          },
          "cancellation_policy": {},
          "option_categories": [
            {
              "label": "amusement-theme-park"
            }
          ],
          "related_locations": [
            {
              "location": {
                "location": {
                  "place_id": "ChIJV2x9oY1JzDER5l8k2n7p4Q"
                }
              },
              "relation_type": "RELATION_TYPE_ADMISSION_TICKET"
            }
          ],
          "price_options": [
            {
              "id": "option-5-per-pax",
              "title": "Per Pax (3–99 yrs)",
              "price": {
                "currency_code": "MYR",
                "units": 48
              }
            }
          ]
        },
        {
          "id": "option-6",
          "title": {
            "localized_texts": [
              {
                "language_code": "en",
                "text": "Breakout NU Sentral [5 - 6 Pax]: Final Hour"
              }
            ]
          },
          "landing_page": {
            "url": "https://www.redbus.my/things-to-do/malaysia/kuala-lumpur/breakout-escape-game-nu-sentral"
          },
          "cancellation_policy": {},
          "option_categories": [
            {
              "label": "amusement-theme-park"
            }
          ],
          "related_locations": [
            {
              "location": {
                "location": {
                  "place_id": "ChIJV2x9oY1JzDER5l8k2n7p4Q"
                }
              },
              "relation_type": "RELATION_TYPE_ADMISSION_TICKET"
            }
          ],
          "price_options": [
            {
              "id": "option-6-per-pax",
              "title": "Per Pax (3–99 yrs)",
              "price": {
                "currency_code": "MYR",
                "units": 45
              }
            }
          ]
        },
        {
          "id": "option-7",
          "title": {
            "localized_texts": [
              {
                "language_code": "en",
                "text": "Breakout NU Sentral [7 - 8 Pax]: Final Hour"
              }
            ]
          },
          "landing_page": {
            "url": "https://www.redbus.my/things-to-do/malaysia/kuala-lumpur/breakout-escape-game-nu-sentral"
          },
          "cancellation_policy": {},
          "option_categories": [
            {
              "label": "amusement-theme-park"
            }
          ],
          "related_locations": [
            {
              "location": {
                "location": {
                  "place_id": "ChIJV2x9oY1JzDER5l8k2n7p4Q"
                }
              },
              "relation_type": "RELATION_TYPE_ADMISSION_TICKET"
            }
          ],
          "price_options": [
            {
              "id": "option-7-per-pax",
              "title": "Per Pax (3–99 yrs)",
              "price": {
                "currency_code": "MYR",
                "units": 42
              }
            }
          ]
        }
      ],
      "related_media": [
        {
          "url": "https://s3.rdbuz.com/activity-images/Activity/659/DSP/659_1.png",
          "type": "MEDIA_TYPE_PHOTO",
          "attribution": {
            "localized_texts": [
              {
                "language_code": "en",
                "text": "Breakout Escape Game NU Sentral"
              }
            ]
          }
        }
      ],
      "inventory_types": [
        "INVENTORY_TYPE_OPERATOR_DIRECT"
      ],
      "operator": {
        "google_business_profile_name": {
          "localized_texts": [
            {
              "language_code": "en",
              "text": "Superdough Sdn Bhd"
            }
          ]
        },
        "locations": [
          {
            "location": {
              "place_id": "ChIJV2x9oY1JzDER5l8k2n7p4Q"
            }
          }
        ]
      }
    }
  ]
}
